{
  "talentData" : {
    "characterClass" : {
      "classId" : 4,
      "name" : "Rogue",
      "powerType" : "ENERGY",
      "powerTypeId" : 3
    },
    "talentTrees" : [ {
      "name" : "Assassination",
      "icon" : "ability_rogue_eviscerate",
      "backgroundFile" : "RogueAssassination",
      "overlayColor" : "#7fcc7f",
      "description" : "A deadly master of poisons who dispatches victims with vicious dagger strikes.",
      "treeNo" : 0,
      "roles" : {
        "tank" : false,
        "healer" : false,
        "dps" : true
      },
      "primarySpells" : [ {
        "spellId" : 1329,
        "name" : "Mutilate",
        "icon" : "ability_rogue_shadowstrikes",
        "cost" : "60 Energy",
        "range" : "Melee Range",
        "castTime" : "Instant",
        "requires" : "Requires Daggers",
        "reagents" : [ ],
        "description" : "Instantly attacks with both weapons for 63% weapon damage plus an additional 7 with each weapon.  Damage is increased by 20% against Poisoned targets.  Awards 2 combo points.",
        "internal" : false,
        "keyAbility" : true
      }, {
        "spellId" : 84601,
        "name" : "Assassin's Resolve",
        "icon" : "ability_rogue_sinistercalling",
        "reagents" : [ ],
        "description" : "While wielding daggers, your maximum Energy is increased by 20 and your melee damage is increased by 15%.",
        "internal" : false,
        "keyAbility" : false
      }, {
        "spellId" : 14117,
        "name" : "Improved Poisons",
        "icon" : "ability_poisons",
        "reagents" : [ ],
        "description" : "Increases the chance to apply Deadly Poison to your target by 20% and the frequency of applying Instant Poison to your target by 50%.",
        "internal" : false,
        "keyAbility" : false
      } ],
      "masteries" : [ {
        "spellId" : 76803,
        "name" : "Potent Poisons",
        "icon" : "trade_brewpoison",
        "reagents" : [ ],
        "description" : "Increases the damage done by your poisons by 28%.  Each point of Mastery increases damage by an additional 3.5%.",
        "internal" : false,
        "keyAbility" : false
      } ],
      "talents" : [ {
        "id" : 6514,
        "name" : "Deadly Momentum",
        "icon" : "ability_rogue_deadlymomentum",
        "x" : 0,
        "y" : 0,
        "ranks" : [ {
          "description" : "After killing an opponent that yields experience or honor, you have a 50% chance to increase the critical strike chance of your next attack within 10 sec by 40%, and to refresh your Slice and Dice and Recuperate abilities to their original duration."
        }, {
          "description" : "After killing an opponent that yields experience or honor, the critical strike chance of your next attack within 10 sec is increased by 40% and your Slice and Dice and Recuperate abilities are refreshed to their original duration."
        } ],
        "keyAbility" : false,
        "categoryMask0" : 0,
        "categoryMask1" : 0
      }, {
        "id" : 276,
        "name" : "Coup de Grace",
        "icon" : "ability_rogue_eviscerate",
        "x" : 1,
        "y" : 0,
        "ranks" : [ {
          "description" : "Increases the damage done by your Eviscerate and Envenom abilities by 7%."
        }, {
          "description" : "Increases the damage done by your Eviscerate and Envenom abilities by 14%."
        }, {
          "description" : "Increases the damage done by your Eviscerate and Envenom abilities by 20%."
        } ],
        "keyAbility" : false,
        "categoryMask0" : 0,
        "categoryMask1" : 0
      }, {
        "id" : 269,
        "name" : "Lethality",
        "icon" : "ability_criticalstrike",
        "x" : 2,
        "y" : 0,
        "ranks" : [ {
          "description" : "Increases the critical strike damage bonus of your Sinister Strike, Backstab, Mutilate and Hemorrhage abilities by 10%."
        }, {
          "description" : "Increases the critical strike damage bonus of your Sinister Strike, Backstab, Mutilate and Hemorrhage abilities by 20%."
        }, {
          "description" : "Increases the critical strike damage bonus of your Sinister Strike, Backstab, Mutilate and Hemorrhage abilities by 30%."
        } ],
        "keyAbility" : false,
        "categoryMask0" : 0,
        "categoryMask1" : 0
      }, {
        "id" : 273,
        "name" : "Ruthlessness",
        "icon" : "ability_druid_disembowel",
        "x" : 0,
        "y" : 1,
        "ranks" : [ {
          "description" : "Gives your melee finishing moves a 20% chance to add a combo point to your target."
        }, {
          "description" : "Gives your melee finishing moves a 40% chance to add a combo point to your target."
        }, {
          "description" : "Gives your melee finishing moves a 60% chance to add a combo point to your target."
        } ],
        "keyAbility" : false,
        "categoryMask0" : 0,
        "categoryMask1" : 0
      }, {
        "id" : 1721,
        "name" : "Quickening",
        "icon" : "ability_rogue_quickrecovery",
        "x" : 1,
        "y" : 1,
        "ranks" : [ {
          "description" : "All healing effects on you are increased by 10% and your movement speed is increased by 8%.  This does not stack with other movement speed increasing effects."
        }, {
          "description" : "All healing effects on you are increased by 20% and your movement speed is increased by 15%.  This does not stack with other movement speed increasing effects."
        } ],
        "keyAbility" : false,
        "categoryMask0" : 0,
        "categoryMask1" : 0
      }, {
        "id" : 277,
        "name" : "Puncturing Wounds",
        "icon" : "ability_backstab",
        "x" : 2,
        "y" : 1,
        "ranks" : [ {
          "description" : "Increases the critical strike chance of your Backstab ability by 10%, and the critical strike chance of your Mutilate ability by 5%."
        }, {
          "description" : "Increases the critical strike chance of your Backstab ability by 20%, and the critical strike chance of your Mutilate ability by 10%."
        }, {
          "description" : "Increases the critical strike chance of your Backstab ability by 30%, and the critical strike chance of your Mutilate ability by 15%."
        } ],
        "keyAbility" : false,
        "categoryMask0" : 0,
        "categoryMask1" : 0
      }, {
        "id" : 6515,
        "name" : "Blackjack",
        "icon" : "ability_rogue_blackjack",
        "x" : 3,
        "y" : 1,
        "ranks" : [ {
          "description" : "Even after your Sap wears off, its effects linger on enemies, reducing their damage done by 35% for 8 sec."
        }, {
          "description" : "Even after your Sap wears off, its effects linger on enemies, reducing their damage done by 70% for 8 sec."
        } ],
        "keyAbility" : false,
        "categoryMask0" : 0,
        "categoryMask1" : 0
      }, {
        "id" : 2065,
        "name" : "Deadly Brew",
        "icon" : "ability_rogue_deadlybrew",
        "x" : 0,
        "y" : 2,
        "ranks" : [ {
          "description" : "When you apply Instant, Wound or Mind-Numbing Poison to a target, you have a 50% chance to apply Crippling Poison."
        }, {
          "description" : "When you apply Instant, Wound, or Mind-Numbing Poison to a target, you have a 100% chance to apply Crippling Poison."
        } ],
        "keyAbility" : false,
        "categoryMask0" : 0,
        "categoryMask1" : 0
      }, {
        "id" : 280,
        "name" : "Cold Blood",
        "icon" : "spell_ice_lament",
        "x" : 1,
        "y" : 2,
        "ranks" : [ {
          "castTime" : "Instant",
          "cooldown" : "2 min cooldown",
          "description" : "When activated, generates 25 Energy and increases the critical strike chance of your next non-periodic offensive ability by 100%."
        } ],
        "keyAbility" : true,
        "categoryMask0" : 0,
        "categoryMask1" : 0
      }, {
        "id" : 682,
        "name" : "Vile Poisons",
        "icon" : "ability_rogue_feigndeath",
        "x" : 2,
        "y" : 2,
        "ranks" : [ {
          "description" : "Increases the damage dealt by your poisons by 7% and gives you 33% of the normal chance of applying poisons from your equipped melee weapons when you use the Fan of Knives ability."
        }, {
          "description" : "Increases the damage dealt by your poisons by 14% and gives you 67% of the normal chance of applying poisons from your equipped melee weapons when you use the Fan of Knives ability."
        }, {
          "description" : "Increases the damage dealt by your poisons by 20% and gives you 100% of the normal chance of applying poisons from your equipped melee weapons when you use the Fan of Knives ability."
        } ],
        "keyAbility" : false,
        "categoryMask0" : 0,
        "categoryMask1" : 0
      }, {
        "id" : 11209,
        "name" : "Deadened Nerves",
        "icon" : "ability_rogue_deadenednerves",
        "x" : 0,
        "y" : 3,
        "ranks" : [ {
          "description" : "Reduces all damage taken by 3%."
        }, {
          "description" : "Reduces all damage taken by 7%."
        }, {
          "description" : "Reduces all damage taken by 10%."
        } ],
        "keyAbility" : false,
        "categoryMask0" : 0,
        "categoryMask1" : 0
      }, {
        "id" : 283,
        "name" : "Seal Fate",
        "icon" : "ability_rogue_stayofexecution",
        "x" : 1,
        "y" : 3,
        "req" : 280,
        "ranks" : [ {
          "description" : "Your critical strikes from abilities that add combo points have a 50% chance to add an additional combo point."
        }, {
          "description" : "Your critical strikes from abilities that add combo points have a 100% chance to add an additional combo point."
        } ],
        "keyAbility" : false,
        "categoryMask0" : 0,
        "categoryMask1" : 0
      }, {
        "id" : 6516,
        "name" : "Murderous Intent",
        "icon" : "spell_shadow_deathscream",
        "x" : 0,
        "y" : 4,
        "ranks" : [ {
          "description" : "When you Backstab an enemy that is below 35% health, you instantly recover 15 Energy."
        }, {
          "description" : "When you Backstab an enemy that is below 35% health, you instantly recover 30 Energy."
        } ],
        "keyAbility" : false,
        "categoryMask0" : 0,
        "categoryMask1" : 0
      }, {
        "id" : 281,
        "name" : "Overkill",
        "icon" : "ability_hunter_rapidkilling",
        "x" : 1,
        "y" : 4,
        "ranks" : [ {
          "description" : "While stealthed, and for 20 seconds after breaking stealth, you regenerate 30% additional energy."
        } ],
        "keyAbility" : false,
        "categoryMask0" : 0,
        "categoryMask1" : 0
      }, {
        "id" : 1715,
        "name" : "Master Poisoner",
        "icon" : "ability_creature_poison_06",
        "x" : 2,
        "y" : 4,
        "req" : 682,
        "ranks" : [ {
          "description" : "Increases the spell damage taken by any target you have poisoned by 8%, causes your Envenom ability to no longer consume Deadly Poison, and reduces the duration of all Poison effects applied to you by 50%."
        } ],
        "keyAbility" : false,
        "categoryMask0" : 0,
        "categoryMask1" : 0
      }, {
        "id" : 278,
        "name" : "Improved Expose Armor",
        "icon" : "ability_warrior_riposte",
        "x" : 3,
        "y" : 4,
        "ranks" : [ {
          "description" : "Gives a 50% chance to refund all combo points used when performing your Expose Armor ability."
        }, {
          "description" : "Gives a 100% chance to refund all combo points used when performing your Expose Armor ability."
        } ],
        "keyAbility" : false,
        "categoryMask0" : 0,
        "categoryMask1" : 0
      }, {
        "id" : 2070,
        "name" : "Cut to the Chase",
        "icon" : "ability_rogue_cuttothechase",
        "x" : 1,
        "y" : 5,
        "ranks" : [ {
          "description" : "Your Eviscerate and Envenom abilities have a 33% chance to refresh your Slice and Dice duration to its 5 combo point maximum."
        }, {
          "description" : "Your Eviscerate and Envenom abilities have a 67% chance to refresh your Slice and Dice duration to its 5 combo point maximum."
        }, {
          "description" : "Your Eviscerate and Envenom abilities have a 100% chance to refresh your Slice and Dice duration to its 5 combo point maximum."
        } ],
        "keyAbility" : false,
        "categoryMask0" : 0,
        "categoryMask1" : 0
      }, {
        "id" : 6517,
        "name" : "Venomous Wounds",
        "icon" : "ability_rogue_venomouswounds",
        "x" : 2,
        "y" : 5,
        "ranks" : [ {
          "description" : "Each time your Rupture or Garrote deals damage to an enemy that you have poisoned, you have a 30% chance to deal 26 additional Nature damage and to regain 10 Energy.  If an enemy dies while afflicted by your Rupture, you regain energy proportional to the remaining Rupture duration."
        }, {
          "description" : "Each time your Rupture or Garrote deals damage to an enemy that you have poisoned, you have a 60% chance to deal 26 additional Nature damage and to regain 10 Energy.  If an enemy dies while afflicted by your Rupture, you regain energy proportional to the remaining Rupture duration."
        } ],
        "keyAbility" : false,
        "categoryMask0" : 0,
        "categoryMask1" : 0
      }, {
        "id" : 2071,
        "name" : "Vendetta",
        "icon" : "ability_rogue_deadliness",
        "x" : 1,
        "y" : 6,
        "ranks" : [ {
          "range" : "30 yd range",
          "castTime" : "Instant cast",
          "cooldown" : "2 min cooldown",
          "description" : "Marks an enemy for death, increasing all damage you deal to the target by 20% and granting you unerring vision of your target, regardless of concealments such as stealth and invisibility.  Lasts 30 sec."
        } ],
        "keyAbility" : true,
        "categoryMask0" : 0,
        "categoryMask1" : 0
      } ]
    }, {
      "name" : "Combat",
      "icon" : "ability_backstab",
      "backgroundFile" : "RogueCombat",
      "overlayColor" : "#ff7f00",
      "description" : "A swashbuckler who uses agility and guile to stand toe-to-toe with enemies.",
      "treeNo" : 1,
      "roles" : {
        "tank" : false,
        "healer" : false,
        "dps" : true
      },
      "primarySpells" : [ {
        "spellId" : 13877,
        "name" : "Blade Flurry",
        "icon" : "ability_warrior_punishingblow",
        "cost" : "25 Energy",
        "castTime" : "Instant",
        "cooldown" : "30 sec cooldown",
        "reagents" : [ ],
        "description" : "While active, the rogue's attacks strike an additional nearby opponent, but energy regeneration is reduced by 20%.  Lasts 15 sec.",
        "internal" : false,
        "keyAbility" : true
      }, {
        "spellId" : 13852,
        "name" : "Ambidexterity",
        "icon" : "ability_dualwield",
        "reagents" : [ ],
        "description" : "Increases the damage done by your off hand and thrown weapons by 75%.",
        "internal" : false,
        "keyAbility" : false
      }, {
        "spellId" : 61329,
        "name" : "Vitality",
        "icon" : "ability_warrior_revenge",
        "reagents" : [ ],
        "description" : "Increases your Energy regeneration rate by 25% and your Attack Power by 20%.",
        "internal" : false,
        "keyAbility" : false
      } ],
      "masteries" : [ {
        "spellId" : 76806,
        "name" : "Main Gauche",
        "icon" : "inv_weapon_shortblade_15",
        "reagents" : [ ],
        "description" : "Your main hand attacks have a 16% chance to grant you an extra off hand attack.  Each point of Mastery increases the chance by an additional 2.00%.",
        "internal" : false,
        "keyAbility" : false
      } ],
      "talents" : [ {
        "id" : 6395,
        "name" : "Improved Recuperate",
        "icon" : "ability_rogue_improvedrecuperate",
        "x" : 0,
        "y" : 0,
        "ranks" : [ {
          "description" : "Causes your Recuperate ability to restore an additional 1% of your maximum health and reduces all damage taken by 3% while your Recuperate ability is active."
        }, {
          "description" : "Causes your Recuperate ability to restore an additional 2% of your maximum health and reduces all damage taken by 6% while your Recuperate ability is active."
        } ],
        "keyAbility" : false,
        "categoryMask0" : 0,
        "categoryMask1" : 0
      }, {
        "id" : 201,
        "name" : "Improved Sinister Strike",
        "icon" : "spell_shadow_ritualofsacrifice",
        "x" : 1,
        "y" : 0,
        "ranks" : [ {
          "description" : "Increases the damage dealt by your Sinister Strike ability by 10% and reduces its Energy cost by 2."
        }, {
          "description" : "Increases the damage dealt by your Sinister Strike ability by 20% and reduces its Energy cost by 4."
        }, {
          "description" : "Increases the damage dealt by your Sinister Strike ability by 30% and reduces its Energy cost by 6."
        } ],
        "keyAbility" : false,
        "categoryMask0" : 0,
        "categoryMask1" : 0
      }, {
        "id" : 181,
        "name" : "Precision",
        "icon" : "ability_marksmanship",
        "x" : 2,
        "y" : 0,
        "ranks" : [ {
          "description" : "Increases your chance to hit with weapon and poison attacks by 2%."
        }, {
          "description" : "Increases your chance to hit with weapon and poison attacks by 4%."
        }, {
          "description" : "Increases your chance to hit with weapon and poison attacks by 6%."
        } ],
        "keyAbility" : false,
        "categoryMask0" : 0,
        "categoryMask1" : 0
      }, {
        "id" : 1827,
        "name" : "Improved Slice and Dice",
        "icon" : "ability_rogue_slicedice",
        "x" : 0,
        "y" : 1,
        "ranks" : [ {
          "description" : "Increases the duration of your Slice and Dice ability by 25%."
        }, {
          "description" : "Increases the duration of your Slice and Dice ability by 50%."
        } ],
        "keyAbility" : false,
        "categoryMask0" : 0,
        "categoryMask1" : 0
      }, {
        "id" : 222,
        "name" : "Improved Sprint",
        "icon" : "ability_rogue_sprint",
        "x" : 1,
        "y" : 1,
        "ranks" : [ {
          "description" : "Gives a 50% chance to remove all movement-impairing effects when you activate your Sprint ability."
        }, {
          "description" : "Gives a 100% chance to remove all movement-impairing effects when you activate your Sprint ability."
        } ],
        "keyAbility" : false,
        "categoryMask0" : 0,
        "categoryMask1" : 0
      }, {
        "id" : 1122,
        "name" : "Aggression",
        "icon" : "ability_racial_avatar",
        "x" : 2,
        "y" : 1,
        "ranks" : [ {
          "description" : "Increases the damage of your Sinister Strike, Backstab, and Eviscerate abilities by 7%."
        }, {
          "description" : "Increases the damage of your Sinister Strike, Backstab, and Eviscerate abilities by 14%."
        }, {
          "description" : "Increases the damage of your Sinister Strike, Backstab, and Eviscerate abilities by 20%."
        } ],
        "keyAbility" : false,
        "categoryMask0" : 0,
        "categoryMask1" : 0
      }, {
        "id" : 206,
        "name" : "Improved Kick",
        "icon" : "ability_kick",
        "x" : 3,
        "y" : 1,
        "ranks" : [ {
          "description" : "Causes your Kick ability to also silence the target for 1.50 sec."
        }, {
          "description" : "Causes your Kick ability to silence the target for 3 sec."
        } ],
        "keyAbility" : false,
        "categoryMask0" : 0,
        "categoryMask1" : 0
      }, {
        "id" : 186,
        "name" : "Lightning Reflexes",
        "icon" : "spell_nature_invisibilty",
        "x" : 0,
        "y" : 2,
        "ranks" : [ {
          "description" : "Increases your chance to dodge enemy attacks by 3% and your attack speed by 2%."
        }, {
          "description" : "Increases your chance to dodge enemy attacks by 6% and your attack speed by 4%."
        }, {
          "description" : "Increases your chance to dodge enemy attacks by 9% and your attack speed by 6%."
        } ],
        "keyAbility" : false,
        "categoryMask0" : 0,
        "categoryMask1" : 0
      }, {
        "id" : 11171,
        "name" : "Revealing Strike",
        "icon" : "inv_sword_97",
        "x" : 1,
        "y" : 2,
        "ranks" : [ {
          "cost" : "40 Energy",
          "range" : "Melee Range",
          "castTime" : "Instant",
          "requires" : "Requires Melee Weapon",
          "description" : "An instant strike that causes 81% of your normal weapon damage and increases the effectiveness of your next offensive finishing move on that target by 20% for 15 sec.  Awards 1 combo point."
        } ],
        "keyAbility" : true,
        "categoryMask0" : 0,
        "categoryMask1" : 0
      }, {
        "id" : 6511,
        "name" : "Reinforced Leather",
        "icon" : "ability_rogue_reinforcedleather",
        "x" : 2,
        "y" : 2,
        "ranks" : [ {
          "description" : "Increases your armor contribution from cloth and leather items by 25%."
        }, {
          "description" : "Increases your armor contribution from cloth and leather items by 50%."
        } ],
        "keyAbility" : false,
        "categoryMask0" : 0,
        "categoryMask1" : 0
      }, {
        "id" : 203,
        "name" : "Improved Gouge",
        "icon" : "ability_gouge",
        "x" : 3,
        "y" : 2,
        "ranks" : [ {
          "description" : "Increases the effect duration of your Gouge ability by 1 sec and reduces its energy cost by 15."
        }, {
          "description" : "Increases the effect duration of your Gouge ability by 2 sec and reduces its energy cost by 30."
        } ],
        "keyAbility" : false,
        "categoryMask0" : 0,
        "categoryMask1" : 0
      }, {
        "id" : 1825,
        "name" : "Combat Potency",
        "icon" : "inv_weapon_shortblade_38",
        "x" : 1,
        "y" : 3,
        "ranks" : [ {
          "description" : "Gives your successful off-hand melee attacks a 20% chance to generate 5 Energy."
        }, {
          "description" : "Gives your successful off-hand melee attacks a 20% chance to generate 10 Energy."
        }, {
          "description" : "Gives your successful off-hand melee attacks a 20% chance to generate 15 Energy."
        } ],
        "keyAbility" : false,
        "categoryMask0" : 0,
        "categoryMask1" : 0
      }, {
        "id" : 1706,
        "name" : "Blade Twisting",
        "icon" : "ability_rogue_bladetwisting",
        "x" : 2,
        "y" : 3,
        "ranks" : [ {
          "description" : "Gives your damaging melee attacks a 20% chance to daze the target, reducing movement speed by 70% for 4 sec."
        }, {
          "description" : "Gives your damaging melee attacks a 40% chance to daze the target, reducing movement speed by 70% for 8 sec."
        } ],
        "keyAbility" : false,
        "categoryMask0" : 0,
        "categoryMask1" : 0
      }, {
        "id" : 2072,
        "name" : "Throwing Specialization",
        "icon" : "ability_rogue_throwingspecialization",
        "x" : 0,
        "y" : 4,
        "ranks" : [ {
          "description" : "Increases the range of Throw and Deadly Throw by 5 yards and gives your Deadly Throw a 50% chance to interrupt the target for 3 sec."
        }, {
          "description" : "Increases the range of Throw and Deadly Throw by 10 yards and gives your Deadly Throw a 100% chance to interrupt the target for 3 sec."
        } ],
        "keyAbility" : false,
        "categoryMask0" : 0,
        "categoryMask1" : 0
      }, {
        "id" : 205,
        "name" : "Adrenaline Rush",
        "icon" : "spell_shadow_shadowworddominate",
        "x" : 1,
        "y" : 4,
        "ranks" : [ {
          "castTime" : "Instant",
          "cooldown" : "3 min cooldown",
          "description" : "Increases your Energy regeneration rate by 100% and your melee attack speed by 20% for 15 sec."
        } ],
        "keyAbility" : true,
        "categoryMask0" : 0,
        "categoryMask1" : 0
      }, {
        "id" : 2074,
        "name" : "Savage Combat",
        "icon" : "ability_creature_disease_03",
        "x" : 2,
        "y" : 4,
        "ranks" : [ {
          "description" : "Increases your total attack power by 2% and all physical damage caused to enemies you have poisoned is increased by 2%."
        }, {
          "description" : "Increases your total attack power by 4% and all physical damage caused to enemies you have poisoned is increased by 4%."
        } ],
        "keyAbility" : false,
        "categoryMask0" : 0,
        "categoryMask1" : 0
      }, {
        "id" : 11174,
        "name" : "Bandit's Guile",
        "icon" : "ability_rogue_preyontheweak",
        "x" : 0,
        "y" : 5,
        "ranks" : [ {
          "description" : "Your Sinister Strike and Revealing Strike abilities have a 33% chance to grant you an evolving insight into an opponent's defenses, increasing damage to that target by up to 30%.  Opponents can adapt over time, negating this benefit, and Striking a different opponent will begin the cycle anew."
        }, {
          "description" : "Your Sinister Strike and Revealing Strike abilities have a 67% chance to grant you an evolving insight into an opponent's defenses, increasing damage to that target by up to 30%.  Opponents can adapt over time, negating this benefit, and Striking a different opponent will begin the cycle anew."
        }, {
          "description" : "Your Sinister Strike and Revealing Strike abilities have a 100% chance to grant you an evolving insight into an opponent's defenses, increasing damage to that target by up to 30%.  Opponents can adapt over time, negating this benefit, and Striking a different opponent will begin the cycle anew."
        } ],
        "keyAbility" : false,
        "categoryMask0" : 0,
        "categoryMask1" : 0
      }, {
        "id" : 6513,
        "name" : "Restless Blades",
        "icon" : "ability_rogue_restlessblades",
        "x" : 2,
        "y" : 5,
        "ranks" : [ {
          "description" : "Your damaging finishing moves reduce the cooldown of your Adrenaline Rush, Killing Spree, and Sprint abilities by 1 sec per combo point."
        }, {
          "description" : "Your damaging finishing moves reduce the cooldown of your Adrenaline Rush, Killing Spree, and Sprint abilities by 2 sec per combo point."
        } ],
        "keyAbility" : false,
        "categoryMask0" : 0,
        "categoryMask1" : 0
      }, {
        "id" : 2076,
        "name" : "Killing Spree",
        "icon" : "ability_rogue_murderspree",
        "x" : 1,
        "y" : 6,
        "req" : 205,
        "ranks" : [ {
          "range" : "10 yd range",
          "castTime" : "Instant",
          "cooldown" : "2 min cooldown",
          "requires" : "Requires Melee Weapon",
          "description" : "Step through the shadows from enemy to enemy within 10 yards, attacking an enemy every .5 secs with both weapons until 5 assaults are made, and increasing all damage done by 20% for the duration.  Can hit the same target multiple times.  Cannot hit invisible or stealthed targets."
        } ],
        "keyAbility" : true,
        "categoryMask0" : 0,
        "categoryMask1" : 0
      } ]
    }, {
      "name" : "Subtlety",
      "icon" : "ability_stealth",
      "backgroundFile" : "RogueSubtlety",
      "overlayColor" : "#4c7fff",
      "description" : "A dark stalker who leaps from the shadows to ambush his unsuspecting prey.",
      "treeNo" : 2,
      "roles" : {
        "tank" : false,
        "healer" : false,
        "dps" : true
      },
      "primarySpells" : [ {
        "spellId" : 36554,
        "name" : "Shadowstep",
        "icon" : "ability_rogue_shadowstep",
        "cost" : "10 Energy",
        "range" : "25 yd range",
        "castTime" : "Instant",
        "cooldown" : "20 sec cooldown",
        "reagents" : [ ],
        "description" : "Causes you to step through the shadows and appear behind an enemy target.  Your next Ambush or Garrote delivered within 10 sec will deal 30% additional damage, and your movement speed is increased by 70% for 3 sec.",
        "internal" : false,
        "keyAbility" : true
      }, {
        "spellId" : 31223,
        "name" : "Master of Subtlety",
        "icon" : "ability_rogue_masterofsubtlety",
        "reagents" : [ ],
        "description" : "Attacks made while stealthed and for 6 seconds after breaking stealth cause an additional 10% damage.",
        "internal" : false,
        "keyAbility" : false
      }, {
        "spellId" : 31220,
        "name" : "Sinister Calling",
        "icon" : "ability_rogue_sinistercalling",
        "reagents" : [ ],
        "description" : "Increases your total Agility by 25% and increases the percentage damage bonus of Backstab and Hemorrhage by an additional 25%.",
        "internal" : false,
        "keyAbility" : false
      } ],
      "masteries" : [ {
        "spellId" : 76808,
        "name" : "Executioner",
        "icon" : "inv_axe_06",
        "reagents" : [ ],
        "description" : "Increases the damage done by all your finishing moves, and the effectiveness of your Slice and Dice, by 16%.  Each point of Mastery increases damage by an additional 2.0%.",
        "internal" : false,
        "keyAbility" : false
      } ],
      "talents" : [ {
        "id" : 244,
        "name" : "Nightstalker",
        "icon" : "ability_stealth",
        "x" : 0,
        "y" : 0,
        "ranks" : [ {
          "description" : "Increases your speed while stealthed by 7% and reduces the cooldown of your Stealth ability by 3 sec."
        }, {
          "description" : "Increases your speed while stealthed by 15% and reduces the cooldown of your Stealth ability by 6 sec."
        } ],
        "keyAbility" : false,
        "categoryMask0" : 0,
        "categoryMask1" : 0
      }, {
        "id" : 263,
        "name" : "Improved Ambush",
        "icon" : "ability_rogue_ambush",
        "x" : 1,
        "y" : 0,
        "ranks" : [ {
          "description" : "Increases the critical strike chance of your Ambush ability by 20% and its damage by 5%."
        }, {
          "description" : "Increases the critical strike chance of your Ambush ability by 40% and its damage by 10%."
        }, {
          "description" : "Increases the critical strike chance of your Ambush ability by 60% and its damage by 15%."
        } ],
        "keyAbility" : false,
        "categoryMask0" : 0,
        "categoryMask1" : 0
      }, {
        "id" : 2244,
        "name" : "Relentless Strikes",
        "icon" : "ability_warrior_decisivestrike",
        "x" : 2,
        "y" : 0,
        "ranks" : [ {
          "description" : "Your finishing moves have a 7% chance per combo point to restore 25 energy."
        }, {
          "description" : "Your finishing moves have a 14% chance per combo point to restore 25 energy."
        }, {
          "description" : "Your finishing moves have a 20% chance per combo point to restore 25 energy."
        } ],
        "keyAbility" : false,
        "categoryMask0" : 0,
        "categoryMask1" : 0
      }, {
        "id" : 247,
        "name" : "Elusiveness",
        "icon" : "spell_magic_lesserinvisibilty",
        "x" : 0,
        "y" : 1,
        "ranks" : [ {
          "description" : "Reduces the cooldown of your Vanish and Blind abilities by 30 sec and your Cloak of Shadows ability by 15 sec."
        }, {
          "description" : "Reduces the cooldown of your Vanish and Blind abilities by 60 sec and your Cloak of Shadows ability by 30 sec."
        } ],
        "keyAbility" : false,
        "categoryMask0" : 0,
        "categoryMask1" : 0
      }, {
        "id" : 2077,
        "name" : "Waylay",
        "icon" : "ability_rogue_waylay",
        "x" : 1,
        "y" : 1,
        "req" : 263,
        "ranks" : [ {
          "description" : "Your Ambush and Backstab hits have a 50% chance to unbalance a target, increasing the time between their melee and ranged attacks by 20%, and reducing movement speed by 50% for 8 sec."
        }, {
          "description" : "Your Ambush and Backstab hits have a 100% chance to unbalance a target, increasing the time between their melee and ranged attacks by 20%, and reducing movement speed by 50% for 8 sec."
        } ],
        "keyAbility" : false,
        "categoryMask0" : 0,
        "categoryMask1" : 0
      }, {
        "id" : 261,
        "name" : "Opportunity",
        "icon" : "ability_rogue_bloodsplatter",
        "x" : 2,
        "y" : 1,
        "ranks" : [ {
          "description" : "Increases the damage dealt with your Backstab, Mutilate, Garrote, and Ambush abilities by 10%."
        }, {
          "description" : "Increases the damage dealt with your Backstab, Mutilate, Garrote and Ambush abilities by 20%."
        }, {
          "description" : "Increases the damage dealt with your Backstab, Mutilate, Garrote and Ambush abilities by 30%."
        } ],
        "keyAbility" : false,
        "categoryMask0" : 0,
        "categoryMask1" : 0
      }, {
        "id" : 245,
        "name" : "Initiative",
        "icon" : "spell_shadow_fumble",
        "x" : 3,
        "y" : 1,
        "ranks" : [ {
          "description" : "Gives you a 50% chance to add an additional combo point to your target when using your Ambush, Garrote, or Cheap Shot ability."
        }, {
          "description" : "Gives you a 100% chance to add an additional combo point to your target when using your Ambush, Garrote, or Cheap Shot ability."
        } ],
        "keyAbility" : false,
        "categoryMask0" : 0,
        "categoryMask1" : 0
      }, {
        "id" : 11665,
        "name" : "Energetic Recovery",
        "icon" : "ability_rogue_sturdyrecuperate",
        "x" : 0,
        "y" : 2,
        "ranks" : [ {
          "description" : "Empowers your Recuperate ability, causing its periodic effect to also restore 4 Energy."
        }, {
          "description" : "Empowers your Recuperate ability, causing its periodic effect to also restore 8 Energy."
        }, {
          "description" : "Empowers your Recuperate ability, causing its periodic effect to also restore 12 Energy."
        } ],
        "keyAbility" : false,
        "categoryMask0" : 0,
        "categoryMask1" : 0
      }, {
        "id" : 6519,
        "name" : "Find Weakness",
        "icon" : "ability_rogue_findweakness",
        "x" : 1,
        "y" : 2,
        "ranks" : [ {
          "description" : "Your Ambush, Garrote, and Cheap Shot abilities reveal a flaw in your target's defenses, causing all your attacks to bypass 25% of that enemy's armor for 10 sec."
        }, {
          "description" : "Your Ambush, Garrote, and Cheap Shot abilities reveal a flaw in your target's defenses, causing all your attacks to bypass 50% of that enemy's armor for 10 sec."
        } ],
        "keyAbility" : false,
        "categoryMask0" : 0,
        "categoryMask1" : 0
      }, {
        "id" : 681,
        "name" : "Hemorrhage",
        "icon" : "spell_shadow_lifedrain",
        "x" : 2,
        "y" : 2,
        "ranks" : [ {
          "cost" : "35 Energy",
          "range" : "Melee Range",
          "castTime" : "Instant",
          "requires" : "Requires Melee Weapon",
          "description" : "An instant strike that deals 69% weapon damage (100% if a dagger is equipped) and causes the target to take 30% additional damage from bleed effects for 1 min.  Awards 1 combo point."
        } ],
        "keyAbility" : true,
        "categoryMask0" : 0,
        "categoryMask1" : 0
      }, {
        "id" : 2078,
        "name" : "Honor Among Thieves",
        "icon" : "ability_rogue_honoramongstthieves",
        "x" : 0,
        "y" : 3,
        "ranks" : [ {
          "description" : "Increases the critical strike chance of all party and raid members by 5%. When any player in your party or raid critically hits with a spell or ability, you have a 33% chance to gain a combo point on your current target.  This effect cannot occur more than once every 4 seconds."
        }, {
          "description" : "Increases the critical strike chance of all party and raid members by 5%. When any player in your party or raid critically hits with a spell or ability, you have a 66% chance to gain a combo point on your current target.  This effect cannot occur more than once every 3 seconds."
        }, {
          "description" : "Increases the critical strike chance of all party and raid members by 5%. When any player in your party or raid critically hits with a spell or ability, you have a 100% chance to gain a combo point on your current target.  This effect cannot occur more than once every 2 seconds."
        } ],
        "keyAbility" : false,
        "categoryMask0" : 0,
        "categoryMask1" : 0
      }, {
        "id" : 381,
        "name" : "Premeditation",
        "icon" : "spell_shadow_possession",
        "x" : 1,
        "y" : 3,
        "ranks" : [ {
          "range" : "30 yd range",
          "castTime" : "Instant",
          "cooldown" : "20 sec cooldown",
          "description" : "When used, adds 2 combo points to your target.  You must add to or use those combo points within 20 sec or the combo points are lost."
        } ],
        "keyAbility" : true,
        "categoryMask0" : 0,
        "categoryMask1" : 0
      }, {
        "id" : 11664,
        "name" : "Enveloping Shadows",
        "icon" : "ability_rogue_envelopingshadows",
        "x" : 3,
        "y" : 3,
        "ranks" : [ {
          "description" : "Reduces the damage taken by area of effect attacks by 10% and increases the duration of your Feint ability by 1 sec."
        }, {
          "description" : "Reduces the damage taken by area of effect attacks by 20% and increases the duration of your Feint ability by 2 sec."
        }, {
          "description" : "Reduces the damage taken by area of effect attacks by 30% and increases the duration of your Feint ability by 3 sec."
        } ],
        "keyAbility" : false,
        "categoryMask0" : 0,
        "categoryMask1" : 0
      }, {
        "id" : 1722,
        "name" : "Cheat Death",
        "icon" : "ability_rogue_cheatdeath",
        "x" : 0,
        "y" : 4,
        "ranks" : [ {
          "description" : "You have a 33% chance that an attack which would otherwise kill you will instead reduce you to 10% of your maximum health. In addition, all damage taken will be reduced by 90% for 3 sec.  This effect cannot occur more than once per minute."
        }, {
          "description" : "You have a 66% chance that an attack which would otherwise kill you will instead reduce you to 10% of your maximum health. In addition, all damage taken will be reduced by 90% for 3 sec.  This effect cannot occur more than once per minute."
        }, {
          "description" : "You have a 100% chance that an attack which would otherwise kill you will instead reduce you to 10% of your maximum health. In addition, all damage taken will be reduced by 90% for 3 sec.  This effect cannot occur more than once per minute."
        } ],
        "keyAbility" : false,
        "categoryMask0" : 0,
        "categoryMask1" : 0
      }, {
        "id" : 284,
        "name" : "Preparation",
        "icon" : "ability_rogue_preparation",
        "x" : 1,
        "y" : 4,
        "ranks" : [ {
          "castTime" : "Instant",
          "cooldown" : "5 min cooldown",
          "description" : "When activated, this ability immediately finishes the cooldown on your Evasion, Sprint, Vanish, and Shadowstep abilities."
        } ],
        "keyAbility" : true,
        "categoryMask0" : 0,
        "categoryMask1" : 0
      }, {
        "id" : 6520,
        "name" : "Sanguinary Vein",
        "icon" : "ability_rogue_sanguinaryvein",
        "x" : 2,
        "y" : 4,
        "req" : 681,
        "ranks" : [ {
          "description" : "Increases your damage dealt to targets with a Bleed effect on them by 5%."
        }, {
          "description" : "Increases your damage dealt to targets who are afflicted with a Bleed effect by 10%."
        } ],
        "keyAbility" : false,
        "categoryMask0" : 0,
        "categoryMask1" : 0
      }, {
        "id" : 2080,
        "name" : "Slaughter from the Shadows",
        "icon" : "ability_rogue_slaughterfromtheshadows",
        "x" : 1,
        "y" : 5,
        "ranks" : [ {
          "description" : "Reduces the energy cost of your Backstab and Ambush abilities by 7, and the energy cost of your Hemorrhage and Fan of Knives abilities by 2."
        }, {
          "description" : "Reduces the energy cost of your Backstab and Ambush abilities by 14, and the energy cost of your Hemorrhage and Fan of Knives abilities by 4."
        }, {
          "description" : "Reduces the energy cost of your Backstab and Ambush abilities by 20, and the energy cost of your Hemorrhage and Fan of Knives abilities by 6."
        } ],
        "keyAbility" : false,
        "categoryMask0" : 0,
        "categoryMask1" : 0
      }, {
        "id" : 1123,
        "name" : "Serrated Blades",
        "icon" : "inv_sword_17",
        "x" : 2,
        "y" : 5,
        "ranks" : [ {
          "description" : "Your Eviscerate has a 10% chance per combo point to refresh your Rupture on the target to its original duration."
        }, {
          "description" : "Your Eviscerate has a 20% chance per combo point to refresh your Rupture on the target to its original duration."
        } ],
        "keyAbility" : false,
        "categoryMask0" : 0,
        "categoryMask1" : 0
      }, {
        "id" : 2081,
        "name" : "Shadow Dance",
        "icon" : "ability_rogue_shadowdance",
        "x" : 1,
        "y" : 6,
        "ranks" : [ {
          "castTime" : "Instant",
          "cooldown" : "1 min cooldown",
          "description" : "Enter the Shadow Dance for 6 sec, allowing the use of Sap, Garrote, Ambush, Cheap Shot, Premeditation, Pickpocket and Disarm Trap regardless of being stealthed."
        } ],
        "keyAbility" : true,
        "categoryMask0" : 0,
        "categoryMask1" : 0
      } ]
    } ]
  }
}